agentic_scrum_setup/__init__.py
agentic_scrum_setup/cli.py
agentic_scrum_setup/codebase_analyzer.py
agentic_scrum_setup/conversational_onboarding.py
agentic_scrum_setup/organization_setup.py
agentic_scrum_setup/repository_manager.py
agentic_scrum_setup/setup_core.py
agentic_scrum_setup/patching/__init__.py
agentic_scrum_setup/patching/discovery.py
agentic_scrum_setup/patching/patcher.py
agentic_scrum_setup/patching/validation.py
agentic_scrum_setup/patching/operations/__init__.py
agentic_scrum_setup/patching/operations/add_animated_banner.py
agentic_scrum_setup/patching/operations/add_background_agents.py
agentic_scrum_setup/patching/operations/add_command.py
agentic_scrum_setup/patching/operations/add_template.py
agentic_scrum_setup/patching/operations/fix_cli.py
agentic_scrum_setup/patching/operations/sync_changes.py
agentic_scrum_setup/patching/operations/update_all.py
agentic_scrum_setup/patching/operations/update_mcp.py
agentic_scrum_setup/patching/operations/update_security.py
agentic_scrum_setup/patching/utils/__init__.py
agentic_scrum_setup/patching/utils/init_sh_parser.py
agentic_scrum_setup/patching/utils/init_sh_parser_old.py
agentic_scrum_setup/patching/utils/init_sh_updater.py
agentic_scrum_setup/patching/utils/mcp_merger.py
agentic_scrum_setup/patching/utils/project_context.py
agentic_scrum_setup/patching/utils/template_renderer.py
agentic_scrum_setup/templates/.env.sample
agentic_scrum_setup/templates/.gitignore.j2
agentic_scrum_setup/templates/README.md.j2
agentic_scrum_setup/templates/agentic_config.yaml.j2
agentic_scrum_setup/templates/agentic_config.yaml.sample.j2
agentic_scrum_setup/templates/generic_persona_rules.yaml.j2
agentic_scrum_setup/templates/generic_priming_script.md.j2
agentic_scrum_setup/templates/persona_rules_advanced.yaml.j2
agentic_scrum_setup/templates/agents/agent_mcp_config.json.j2
agentic_scrum_setup/templates/checklists/code_review_checklist.md.j2
agentic_scrum_setup/templates/checklists/definition_of_done.md.j2
agentic_scrum_setup-1.0.0b10.dist-info/licenses/LICENSE
agentic_scrum_setup-1.0.0b10.dist-info/METADATA
agentic_scrum_setup-1.0.0b10.dist-info/WHEEL
agentic_scrum_setup-1.0.0b10.dist-info/entry_points.txt
agentic_scrum_setup-1.0.0b10.dist-info/top_level.txt
agentic_scrum_setup-1.0.0b10.dist-info/RECORD
